[
{
    "model": "auth.user",
    "pk": 1,
    "fields": {
        "password": "Qazedc357",
        "last_login": null,
        "is_superuser": false,
        "username": "QWEwq",
        "first_name": "Qwe",
        "last_name": "Ewq",
        "email": "",
        "is_staff": false,
        "is_active": true,
        "date_joined": "2022-11-03T10:36:26.675Z",
        "groups": [],
        "user_permissions": []
    }
},
{
    "model": "auth.user",
    "pk": 2,
    "fields": {
        "password": "Aezakmi357",
        "last_login": null,
        "is_superuser": false,
        "username": "TestUser2",
        "first_name": "name2",
        "last_name": "last2",
        "email": "",
        "is_staff": false,
        "is_active": true,
        "date_joined": "2022-11-03T10:37:26.675Z",
        "groups": [],
        "user_permissions": []
    }
}
]

